{
  "name": "Cosmic Baton Girl コメットさん☆",
  "info_box": {
    "中文名: ": "彗星公主",
    "话数: ": "43",
    "放送开始: ": "2001年4月1日",
    "原作: ": [
      "横山光輝"
    ],
    "导演: ": [
      "神戸守"
    ],
    "脚本: ": [
      "桶谷顕"
    ],
    "分镜: ": [
      "川崎逸朗",
      "佐土原武之",
      "佐藤卓哉",
      "寺東克己",
      "福島利規",
      "中村憲由",
      "小高義規"
    ],
    "演出: ": [
      "佐土原武之",
      "福島利規",
      "高島大輔",
      "中村憲由"
    ],
    "音乐: ": [
      "MOKA☆"
    ],
    "作画监督: ": [
      "小林一三",
      "小丸敏之"
    ],
    "原画: ": [
      "佐藤雅弘",
      "木村豪",
      "山崎登志樹"
    ],
    "製作: ": [
      "東宝"
    ],
    "制片人: ": [
      "釜秀樹",
      "斎春雄"
    ],
    "动画制作: ": [
      "日本アニメーション"
    ],
    "副导演: ": [
      "平尾みほ"
    ],
    "别名: ": "音乐小彗星",
    "播放结束: ": "2002年1月27日",
    "原案: ": "国際放映",
    "人物设定: ": "まきだかずあき"
  },
  "attitude": [
    "72人想看",
    "158人看过",
    "7人在看",
    "21人搁置",
    "16人抛弃"
  ],
  "label": [
    {
      "label": "TVB",
      "number": "31"
    },
    {
      "label": "治愈系",
      "number": "22"
    },
    {
      "label": "童年",
      "number": "21"
    },
    {
      "label": "TV",
      "number": "20"
    },
    {
      "label": "2001",
      "number": "13"
    },
    {
      "label": "日本アニメーション",
      "number": "11"
    },
    {
      "label": "动画",
      "number": "9"
    },
    {
      "label": "魔法少女",
      "number": "8"
    },
    {
      "label": "2001年",
      "number": "7"
    },
    {
      "label": "子供向",
      "number": "4"
    },
    {
      "label": "TVA",
      "number": "3"
    },
    {
      "label": "治愈",
      "number": "2"
    },
    {
      "label": "奇幻",
      "number": "1"
    }
  ],
  "score": {
    "global_score": "6.9",
    "score_chart": [
      {
        "label": "10",
        "count": "(2)"
      },
      {
        "label": "9",
        "count": "(5)"
      },
      {
        "label": "8",
        "count": "(17)"
      },
      {
        "label": "7",
        "count": "(48)"
      },
      {
        "label": "6",
        "count": "(17)"
      },
      {
        "label": "5",
        "count": "(6)"
      },
      {
        "label": "4",
        "count": "(3)"
      },
      {
        "label": "3",
        "count": "(0)"
      },
      {
        "label": "2",
        "count": "(0)"
      },
      {
        "label": "1",
        "count": "(0)"
      }
    ]
  },
  "summary": [
    "在三角星云世界里，三个地区的星国联合举办了舞会，手鼓星国的王子被安排在舞会中选择未来一半，王子要在彗星公主或是流星公主两人之间择一当新娘。不过王子决定逃离这一切，到地球流浪，两位公主便带她们各自的宠物，追随王子到地球。",
    "\r\n",
    "\r\n懂得使用星之魔法的彗星，以及她的宠物小波波到达地球后，对环境并不熟识，幸好交到好朋友双胞胎藤吉刚和藤吉宁宁，只有四岁的两人是计算机高手，经常帮助彗星公主。另一方面，流星以及她的宠物默克（毛毛）也在地球寻找王子。在地球上，彗星将会学到很多道理，并且慢慢地成长……"
  ],
  "user_intros": [
    {
      "job": "主角",
      "name": "コメット / 彗星",
      "cv": [
        "前田亜季"
      ]
    },
    {
      "job": "配角",
      "name": "メテオ / 流星",
      "cv": [
        "本多知恵子"
      ]
    }
  ],
  "complaints": [
    "只找到22集之后的英文字幕，前面生肉。星国的设定有些浪费，还是日常系魔法少女。脚本力实在不行",
    "20220418:少有的主角为十三四岁小女孩却全程没有去上学一直在小镇里瞎逛的大友动画，OP、ED都很好听，特别是两个ED的舞棒很可爱。主题秉承着经典魔法少女动画的主旨“魔法不能解决所有事情”，要寻找的王子就是你朝夕相处的男孩的设定十分富有青梅竹马精神。经典魔法少女还有个主旨就是“离去”，在本剧中就是星星公主们回到星星王国，虽然最后又回到了地球，那只不过是作者对观众多此一举的怜悯而已。",
    "星空卫视！应该没看完不过一半应该随缘地扫过了。主题曲被许多人翻唱过，包括早已解散的香港的cookies。歌词简单易懂，日文版曾经在我MP3之类的设备里常驻",
    "二刷日语版，时隔多年再次重刷只能说真的好看，我一直喜欢彗星，现在最喜欢彗星和流星了，都是很好的公主，尤其最后一集，公主的霸气回应，真的太好看了，以前想学指挥棒来着，但是太难了，流星公主的角色歌难以忘记，流星真棒。",
    "我搜星星公主的时候搜出这个来...有时间看一看",
    "11，41神回，女主又成熟又有想法，真是可爱。",
    "儿时的初恋",
    "非常好看，非常好的一部动画！彗星这种自信乐观，现在的动画太少了。要给后代看的动画系列。。。",
    "女主你太悲惨了，快点穿越到70年代的东映魔法少女系列里去吧……女主的配音超赞（虽然完全不是萝莉音），淫兽的也不错。与此形成鲜明对比的是，女主老娘的配音简直是灾难……",
    "我童年怎么跳过这么多坑？还是横山光辉？"
  ],
  "comments": [
    "棒打百变小樱，脚踢DoReMi。童年两大回忆：GG向数码暴龙，MM向音乐小彗星。GG向就一个龙珠竞争，MM向还有百变小樱和外星BB，最终想了一下还是彗星最好！虽然出身权贵，拥有魔法。但这些都不是喜欢她的理由。彗星的乐观，自信，热心，温柔像明灯。\r\n\r\n内容记得个大概，一对双胞胎小萝莉 ... ",
    "整个动画讨论爱情都比较含糊，只有小球球和小精灵是一见钟情的爱，其他都有认真刻画\r\n\r\n\r\n金井舜和流星，彗星的关系：\r\n舜之所以喜欢过彗星是因为她曾经无私地帮助他解脱困境，但是这是一种感恩不是爱，而对于一直在身边的流星来说，她的坚持和帮助一定能感动他的，而且之后作为pa ... "
  ]
}