{
  "name": "タイガーマスクW",
  "info_box": {
    "中文名: ": "虎面人W",
    "话数: ": "38",
    "放送开始: ": "2016年10月1日",
    "放送星期: ": "星期六",
    "原作: ": [
      "梶原一騎",
      "辻なおき"
    ],
    "导演: ": [
      "小村敏明"
    ],
    "脚本: ": [
      "玉井☆豪",
      "あみやまさはる",
      "千葉克彦",
      "米村正二",
      "浦沢義雄"
    ],
    "分镜: ": [
      "西田正義",
      "小村敏明",
      "柳沢テツヤ",
      "鎌谷悠",
      "畑野森生",
      "スタジオモリコーネ",
      "芝田浩樹",
      "地岡公俊",
      "園田誠",
      "勝間田具治",
      "角銅博之",
      "渡邊巧大"
    ],
    "演出: ": [
      "小村敏明",
      "畑野森生",
      "芝田浩樹",
      "地岡公俊",
      "中野武蔵",
      "後藤康徳",
      "園田誠",
      "広嶋秀樹",
      "鎌谷悠",
      "山口暁生",
      "勝間田具治",
      "境宗久",
      "角銅博之"
    ],
    "音乐: ": [
      "高梨康治",
      "刃-yaiba-"
    ],
    "人物设定: ": [
      "香川久"
    ],
    "系列构成: ": [
      "千葉克彦"
    ],
    "美术监督: ": [
      "杦浦正一郎"
    ],
    "总作画监督: ": [
      "井上栄作",
      "香川久"
    ],
    "作画监督: ": [
      "島崎望",
      "小林一三",
      "太田晃博",
      "林隆祥",
      "渡邊巧大",
      "大西亮",
      "大西陽一",
      "香川久",
      "こかいゆうじ",
      "小泉昇",
      "浅沼昭弘",
      "斉藤和也",
      "羽山淳一",
      "横田守",
      "生田目康裕",
      "中野彰子",
      "阿部弘樹",
      "井上栄作",
      "ノエル・アンニョンヌエボ"
    ],
    "原画: ": [
      "田中夕梨子",
      "佐藤滋記",
      "服部森樹朗",
      "橋森有加",
      "伊藤弘樹",
      "鈴木勇真",
      "池田あづさ",
      "牛来隆行",
      "上原真生人",
      "中曽根詩織",
      "泉恭子",
      "河野美由紀",
      "永木龍博",
      "レスティ・ロケ",
      "上田温子",
      "山本拓美",
      "倉持彩乃",
      "なかじまちゅうじ",
      "小林一三",
      "村山里野",
      "大西亮",
      "渡邊巧大",
      "杉江敏治",
      "太田晃博",
      "西野武志",
      "小泉昇",
      "北崎正浩",
      "島崎望",
      "飯飼一幸",
      "大橋勇吾"
    ],
    "剪辑: ": [
      "吉田公紀"
    ],
    "主题歌演出: ": [
      "湘南乃風"
    ],
    "录音: ": [
      "立花康夫"
    ],
    "製作: ": [
      "東映アニメーション"
    ],
    "补间动画: ": [
      "森佳祐",
      "大久保俊介"
    ],
    "助理制片人: ": [
      "遠藤一樹"
    ],
    "制片人: ": [
      "柳井寛史"
    ],
    "动画制作: ": [
      "東映アニメーション"
    ],
    "美术设计: ": [
      "渡辺佳人"
    ],
    "别名: ": "虎头假面W",
    "官方网站: ": "http://www.toei-anim.co.jp/tv/tigermask_w/",
    "播放电视台: ": "テレビ朝日",
    "播放结束: ": "2017年7月1日",
    "Copyright: ": "©梶原一騎・辻なおき/講談社 ©テレビ朝日・東映アニメーション",
    "动作作画监督: ": "羽山淳一"
  },
  "attitude": [
    "103人想看",
    "116人看过",
    "23人在看",
    "24人搁置",
    "57人抛弃"
  ],
  "label": [
    {
      "label": "TV",
      "number": "33"
    },
    {
      "label": "东映",
      "number": "31"
    },
    {
      "label": "2016",
      "number": "26"
    },
    {
      "label": "2016年10月",
      "number": "24"
    },
    {
      "label": "漫改",
      "number": "16"
    },
    {
      "label": "東映アニメーション",
      "number": "14"
    },
    {
      "label": "漫画改",
      "number": "14"
    },
    {
      "label": "竞技",
      "number": "8"
    },
    {
      "label": "战斗",
      "number": "7"
    },
    {
      "label": "草尾毅",
      "number": "3"
    },
    {
      "label": "高梨康治",
      "number": "2"
    },
    {
      "label": "东映动画",
      "number": "2"
    },
    {
      "label": "热血",
      "number": "2"
    },
    {
      "label": "日本动画",
      "number": "2"
    },
    {
      "label": "TVA",
      "number": "2"
    },
    {
      "label": "旧物",
      "number": "1"
    },
    {
      "label": "2016年",
      "number": "1"
    }
  ],
  "score": {
    "global_score": "7.2",
    "score_chart": [
      {
        "label": "10",
        "count": "(6)"
      },
      {
        "label": "9",
        "count": "(4)"
      },
      {
        "label": "8",
        "count": "(24)"
      },
      {
        "label": "7",
        "count": "(38)"
      },
      {
        "label": "6",
        "count": "(14)"
      },
      {
        "label": "5",
        "count": "(9)"
      },
      {
        "label": "4",
        "count": "(1)"
      },
      {
        "label": "3",
        "count": "(0)"
      },
      {
        "label": "2",
        "count": "(0)"
      },
      {
        "label": "1",
        "count": "(0)"
      }
    ]
  },
  "summary": [
    "初代虎面人伊达直人所留下的虎面人遗产，被新的摔角手们继承……！与复活的组织·虎之穴所展开的新战斗传达到了现代！",
    "\r\n现代的虎面人有两人！？",
    "\r\n主人公是“东直人”“藤井拓真”两名年轻的摔角手。他们是职业摔跤小团体“Jipang职业摔角”的练习生，但“Jipang职业摔角”被恶质的职业摔角团体“GWM”击溃了。为了复仇，直人在富士的裾野接受了训练成为“新虎面人”，另一方面拓真则进入了“虎之穴”，成为了“黑暗之虎”。",
    "\r\n“光之虎”与“暗之虎”，等待着两人的战斗与友情将去往何方！？"
  ],
  "user_intros": [
    {
      "job": "主角",
      "name": "東ナオト",
      "cv": [
        "八代拓"
      ]
    },
    {
      "job": "主角",
      "name": "藤井タクマ",
      "cv": [
        "梅原裕一郎"
      ]
    },
    {
      "job": "主角",
      "name": "高岡春奈",
      "cv": [
        "三森すずこ"
      ]
    },
    {
      "job": "配角",
      "name": "オーディン / 奥丁",
      "cv": [
        "竹本英史"
      ]
    },
    {
      "job": "配角",
      "name": "マイク・ロドリゲス / 迈克・罗德里格斯",
      "cv": [
        "内匠靖明"
      ]
    },
    {
      "job": "配角",
      "name": "ケビン・アンダーソン / 凯文・安德森",
      "cv": [
        "福山潤"
      ]
    },
    {
      "job": "配角",
      "name": "オカダ・カズチカ",
      "cv": [
        "森田成一"
      ]
    },
    {
      "job": "配角",
      "name": "棚橋弘至",
      "cv": [
        "鈴村健一"
      ]
    },
    {
      "job": "配角",
      "name": "高岡拳太郎",
      "cv": [
        "田中亮一"
      ]
    }
  ],
  "complaints": [
    "第二遍，如果上帝自己会拍一部致敬经典作品的动画，它大概就会按照本作的样子来拍，香川久的作画真的无时无刻不让我想起同社那帮暴力女子天团啊，最终集一出就是这个经典的feel，闹了半天原来这种像昭和年代风格的女子打架风格的作品在虎面人w里，梶原一骑老师在天之灵估计会很欣慰吧，女主大概也是本人最喜欢的10s动画女角色了（A+，10s前五）",
    "太赞了以至于给我带来了学剪辑的动力",
    "超级系摔跤，莫名合口味",
    "7+",
    "相当优秀的格斗动画",
    "珍惜下还有猛虎原爆固定的时候吧",
    "哲♂学摔跤，贼好看",
    "还蛮喜欢八代拓的",
    "有惊喜，不过总体残念。大西亮的作画和马越的ed很棒。",
    "未及预期，没公主q娃的打戏惊艳，摔跤也正如楼下所谓的超级系般摔得很不真实。文戏作画也不是很稳，还有无聊的灌水回。虽然题材值得推荐，但我实在不想给高分。"
  ],
  "comments": []
}