{
  "name": "この素晴らしい世界に祝福を！2",
  "info_box": {
    "中文名: ": "为美好的世界献上祝福！ 第二季",
    "话数: ": "10",
    "放送开始: ": "2017年1月11日",
    "放送星期: ": "星期三",
    "原作: ": [
      "暁なつめ"
    ],
    "导演: ": [
      "金﨑貴臣"
    ],
    "脚本: ": [
      "待田堂子",
      "上江洲誠",
      "中村浩二郎"
    ],
    "分镜: ": [
      "金﨑貴臣",
      "江原康之",
      "小岩井礼文",
      "斉藤哲人"
    ],
    "演出: ": [
      "江原康之",
      "鈴木孝聡",
      "岩本保雄",
      "吉田俊司",
      "中山敦史",
      "久保太郎"
    ],
    "音乐: ": [
      "甲田雅人"
    ],
    "人物原案: ": [
      "三嶋くろね"
    ],
    "人物设定: ": [
      "菊田幸一"
    ],
    "系列构成: ": [
      "上江洲誠"
    ],
    "美术监督: ": [
      "三宅昌和"
    ],
    "色彩设计: ": [
      "吉田沙織"
    ],
    "总作画监督: ": [
      "田中紀衣",
      "江原康之",
      "菊田幸一"
    ],
    "作画监督: ": [
      "石川洋一",
      "西川真人",
      "出野喜則",
      "田中紀衣",
      "佐藤このみ",
      "中澤勇一",
      "鵜池一馬",
      "林隆祥",
      "浅井昭人",
      "菊田幸一",
      "清水勝祐",
      "さのえり",
      "伊藤康裕",
      "摺木沙織",
      "胡陽樹"
    ],
    "摄影监督: ": [
      "米澤寿",
      "DEEN Digital"
    ],
    "道具设计: ": [
      "伊藤康裕"
    ],
    "原画: ": [
      "坂口蒼星",
      "島村毬子",
      "水谷汐里",
      "河口真緒",
      "金﨑貴臣",
      "昆富美子",
      "岩澤亨",
      "細川智代",
      "地崎義生",
      "小倉せれん",
      "小澤和則",
      "伊藤康裕",
      "佐藤利幸",
      "田中宏紀",
      "内山光",
      "澁川大祐",
      "高橋健",
      "申榮淳",
      "杉田柊",
      "小川莉奈",
      "内田大晟",
      "木下ゆうき",
      "藤本航己",
      "青木康哲",
      "小林之浩",
      "岡崎伸浩",
      "重国浩子",
      "菊田幸一",
      "高橋しんや",
      "吉川知希"
    ],
    "第二原画: ": [
      "水谷汐里",
      "松尾信之",
      "澁川大祐",
      "小島真清",
      "村上彩香",
      "わたなべひろし",
      "津久井快"
    ],
    "动画检查: ": [
      "澁川大祐"
    ],
    "主题歌演出: ": [
      "Machico",
      "雨宮天",
      "高橋李依",
      "茅野愛衣"
    ],
    "企画: ": [
      "菊池剛",
      "工藤大丈"
    ],
    "录音: ": [
      "山口貴之"
    ],
    "製作: ": [
      "KADOKAWA",
      "クロックワークス",
      "スタジオディーン",
      "日本コロムビア",
      "81プロデュース",
      "ソニー・ミュージックソリューションズ",
      "角川メディアハウス",
      "コミックとらのあな",
      "サミー",
      "MAGES.",
      "堀内大示",
      "武智恒雄",
      "野口和紀",
      "北條真",
      "南沢道義",
      "井口健一",
      "篠崎文彦",
      "鮎澤慎二郎",
      "徳村憲一",
      "志倉千代丸"
    ],
    "音响监督: ": [
      "岩浪美和"
    ],
    "音响: ": [
      "HALF H・P STUDIO"
    ],
    "音效: ": [
      "小山恭正"
    ],
    "特效: ": [
      "斉藤丈史"
    ],
    "补间动画: ": [
      "村上彩香"
    ],
    "制片人: ": [
      "小倉理絵"
    ],
    "音乐制作: ": [
      "日本コロムビア"
    ],
    "动画制作: ": [
      "スタジオディーン"
    ],
    "美术设计: ": [
      "藤井一志"
    ],
    "副导演: ": [
      "吉田俊司"
    ],
    "OP・ED 分镜: ": [
      "金﨑貴臣"
    ],
    "3DCG: ": [
      "DEEN Digital"
    ],
    "动画制片人: ": [
      "浦崎宣光"
    ],
    "别名: ": "Kono Subarashii Sekai ni Shukufuku o! 2",
    "官方网站: ": "http://konosuba.com/",
    "播放电视台: ": "TOKYO MX",
    "其他电视台: ": "サンテレビ / TVQ九州放送 / 岐阜放送 / 三重テレビ放送 / テレビ埼玉 / チバテレビ / テレビ神奈川 / BS11",
    "播放结束: ": "2017年3月15日",
    "Copyright: ": "© 2017 暁なつめ・三嶋くろね／KADOKAWA／このすば2製作委員会"
  },
  "attitude": [
    "1173人想看",
    "15149人看过",
    "490人在看",
    "287人搁置",
    "124人抛弃"
  ],
  "label": [
    {
      "label": "搞笑",
      "number": "2679"
    },
    {
      "label": "轻小说改",
      "number": "1776"
    },
    {
      "label": "异世界",
      "number": "1556"
    },
    {
      "label": "2017年1月",
      "number": "1371"
    },
    {
      "label": "为美好的世界献上祝福！",
      "number": "1170"
    },
    {
      "label": "TV",
      "number": "1004"
    },
    {
      "label": "studiodeen",
      "number": "806"
    },
    {
      "label": "后宫",
      "number": "643"
    },
    {
      "label": "轻改",
      "number": "607"
    },
    {
      "label": "2017",
      "number": "502"
    },
    {
      "label": "雨宮天",
      "number": "332"
    },
    {
      "label": "奇幻",
      "number": "304"
    },
    {
      "label": "第二季",
      "number": "266"
    },
    {
      "label": "高桥李依",
      "number": "225"
    },
    {
      "label": "穿越",
      "number": "109"
    },
    {
      "label": "小说改",
      "number": "74"
    },
    {
      "label": "日常",
      "number": "67"
    },
    {
      "label": "续作",
      "number": "51"
    },
    {
      "label": "战斗",
      "number": "47"
    },
    {
      "label": "STUDIO_DEEN",
      "number": "43"
    },
    {
      "label": "冒险",
      "number": "42"
    },
    {
      "label": "为美好的世界献上祝福",
      "number": "33"
    },
    {
      "label": "逗比",
      "number": "32"
    },
    {
      "label": "2017年",
      "number": "28"
    },
    {
      "label": "茅野爱衣",
      "number": "20"
    },
    {
      "label": "素晴",
      "number": "19"
    },
    {
      "label": "崩坏",
      "number": "18"
    }
  ],
  "score": {
    "global_score": "7.6",
    "score_chart": [
      {
        "label": "10",
        "count": "(349)"
      },
      {
        "label": "9",
        "count": "(713)"
      },
      {
        "label": "8",
        "count": "(4551)"
      },
      {
        "label": "7",
        "count": "(3317)"
      },
      {
        "label": "6",
        "count": "(718)"
      },
      {
        "label": "5",
        "count": "(143)"
      },
      {
        "label": "4",
        "count": "(33)"
      },
      {
        "label": "3",
        "count": "(6)"
      },
      {
        "label": "2",
        "count": "(0)"
      },
      {
        "label": "1",
        "count": "(10)"
      }
    ]
  },
  "summary": [
    "由于意外事故而在异世界转生，热爱游戏的家里蹲·佐藤和真， 与“在如同RPG游戏一样的异世界，享受憧憬的冒险者生活！目标勇者！” 这样的梦想失之交臂，但也总算是有模有样地开始在异世界生活。 作为转生的特典被他带来同行的女神·阿库娅。每天只能击出一发魔法的大魔法师·惠惠。攻击总是打不中的十字骑士·达克妮丝。与虽然能力很高却残念到无可救药的3名队友一起，总算是习惯了每天做任务的生活。 ——就在这样的某一天。在为了从机动要塞毁灭者的威胁当中拯救阿克塞尔镇的和真一行人面前，来自王都的使者宣言道。“冒险者，佐藤和真。你现在被怀疑犯下颠覆国家罪！”……平凡的冒险者·和真所度过的异世界生活将迎来怎样的明天！？"
  ],
  "user_intros": [
    {
      "job": "主角",
      "name": "佐藤和真 / 佐藤和真",
      "cv": [
        "福島潤"
      ]
    },
    {
      "job": "主角",
      "name": "アクア / 阿克娅",
      "cv": [
        "雨宮天"
      ]
    },
    {
      "job": "主角",
      "name": "めぐみん / 惠惠",
      "cv": [
        "高橋李依"
      ]
    },
    {
      "job": "主角",
      "name": "ダクネス / 达克妮斯",
      "cv": [
        "茅野愛衣"
      ]
    },
    {
      "job": "配角",
      "name": "クリス / 克莉丝",
      "cv": [
        "諏訪彩花"
      ]
    },
    {
      "job": "配角",
      "name": "エリス / 厄里斯",
      "cv": [
        "諏訪彩花"
      ]
    },
    {
      "job": "配角",
      "name": "ウィズ / 维斯",
      "cv": [
        "堀江由衣"
      ]
    },
    {
      "job": "配角",
      "name": "ゆんゆん / 芸芸",
      "cv": [
        "豊崎愛生"
      ]
    },
    {
      "job": "配角",
      "name": "ルナ / 露娜",
      "cv": [
        "原紗友里"
      ]
    }
  ],
  "complaints": [
    "虽然制作一言难尽，但是看得很舒服的作品",
    "最后一集怎么还燃起来了233",
    "比第一季搞笑不少 荤段子也多了不少",
    "作监睡着了？",
    "难得的原作不烂尾，动画不瞎改且好玩好笑的作品，虽然制作贫穷了点，但是值得看",
    "和真死了还能活过来",
    "乐，真的笑不活了。两季的ed都很好听，有点治愈，好吧看这个番真的能让我从异次元中获得治愈。三个女主都很喜欢捏",
    "挺有趣的，第一时间想到的比较对象是舅舅，虽然同是以角色为核心制造笑点的反传统异世界片，但素晴侧重点在于角色无厘头互动间的构建的日常，奇葩性格角色之间的互动形成了人际关系的稳定感，本作的各种骚乱建立在这层稳定的人际关系上，使得无厘头中带着一丝认真生活的态度。",
    "樂樂",
    "快出第三季吧"
  ],
  "comments": [
    "虽然原作没有看完，但就动画本身来讲，我的感觉就是该作试图以一种反王道的演出来完成王道的剧情展开。所以，为了完成这个命题，不仅男主佐藤和真必须下流卑鄙，他的团队成员也必须在才能或人格上存在某种遗憾的缺陷才行。然而，正是这些任谁看来都属于无药可救的糟糕人物 ... ",
    "啊，真的太搞笑了(bgm38)\r\n我在被窝里看这个番从头笑到尾差点被我妈发现我晚上不睡觉在偷偷看番\r\n而且最后一话战斗的质量空前的高\r\n看之前有人告诉我这个番和慎重勇者有点相似\r\n就是把人物表情夸张化增加搞笑元素来减弱因经费不足的观看体验\r\n但现在我觉得并不是\r\n因 ... ",
    "接着标题的是“这部番的特点很明显——崩坏的画面”，除此之外几乎再无巨大的缺点，那些细小的缺点会被这么巨大的缺点所掩盖。那么随之而来的评论是什么？\r\n“这动画除了崩之外，还挺有趣的。”\r\n“动画剧情很好，就是作画崩。”\r\n在我看来，这就是1月黑马的真相，原作剧情强悍 ... ",
    "好久没写动画，之前和某位女士聊动画，她说里面的妹子都很可爱。\r\n考验死宅的时候到了。\r\nA：附和并列举萌杀你的各路妹子\r\nB：反讽韩剧的帅哥都很帅\r\nC：先附和，然后解释说明“萌元素”，再列举动画吸引人的其它地方\r\nD：看着对方眼睛，微微一笑，不说话\r\n\r\n以下是今年我有记忆的萌系动 ... "
  ]
}