{
  "name": "超可動ガール1/6",
  "info_box": {
    "中文名: ": "超可动女孩1/6",
    "话数: ": "12",
    "放送开始: ": "2019年4月6日",
    "放送星期: ": "星期六",
    "导演: ": [
      "元永慶太郎"
    ],
    "脚本: ": [
      "日暮茶坊"
    ],
    "分镜: ": [
      "東海林真一",
      "大野和寿",
      "元永慶太郎",
      "飯田崇",
      "飯島正勝"
    ],
    "演出: ": [
      "ながはまのりひこ",
      "蔵本穂高"
    ],
    "人物设定: ": [
      "山名秀和"
    ],
    "系列构成: ": [
      "日暮茶坊"
    ],
    "美术监督: ": [
      "滝口勝久"
    ],
    "色彩设计: ": [
      "後藤恵子"
    ],
    "总作画监督: ": [
      "松尾真彦",
      "山名秀和"
    ],
    "作画监督: ": [
      "園田高明",
      "藤田正幸",
      "谷口義明",
      "はっとりますみ",
      "梶浦紳一郎"
    ],
    "摄影监督: ": [
      "山根裕二郎"
    ],
    "原画: ": [
      "佐藤篤志",
      "菅原早也花",
      "桑島望",
      "中島達央",
      "吉岡丈雄",
      "藤田麻貴",
      "吉開順子",
      "寺谷瑠宇公",
      "高田玲大",
      "冨永和代",
      "宇津木勇",
      "小林勝利",
      "津野満代",
      "はっとりますみ",
      "河原久美子",
      "大河原晴男",
      "増田敏彦",
      "浅田真里",
      "松尾真彦",
      "岡田雅人",
      "園田高明",
      "那須野文",
      "津熊健徳",
      "宮崎康子",
      "江藤大気",
      "梶原悠里",
      "菊池一真",
      "森山剛史"
    ],
    "剪辑: ": [
      "木村祥明"
    ],
    "主题歌编曲: ": [
      "前口渉"
    ],
    "主题歌作曲: ": [
      "James Panda Jr."
    ],
    "主题歌演出: ": [
      "A応P",
      "東城陽奏"
    ],
    "音响监督: ": [
      "阿部信行"
    ],
    "制片人: ": [
      "佐藤俊亮"
    ],
    "动画制作: ": [
      "studio A-CAT"
    ],
    "CG 导演: ": [
      "後藤優一"
    ],
    "美术设计: ": [
      "滝口勝久"
    ],
    "副导演: ": [
      "ながはまのりひこ"
    ],
    "3DCG: ": [
      "後藤優一",
      "UWAN PICTURES"
    ],
    "官方网站: ": "http://choukadou-anime.com/",
    "播放电视台: ": "AT-X",
    "其他电视台: ": "TOKYO MX / BSフジ",
    "播放结束: ": "2019年6月22日",
    "Copyright: ": "©ÖYSTER／双葉社・「超可動ガール1/6」製作委員会",
    "原作: ": "ÖYSTER",
    "共同演出: ": "ながはまのりひこ（7-8话）"
  },
  "attitude": [
    "129人想看",
    "439人看过",
    "38人在看",
    "32人搁置",
    "48人抛弃"
  ],
  "label": [
    {
      "label": "泡面番",
      "number": "70"
    },
    {
      "label": "2019年4月",
      "number": "59"
    },
    {
      "label": "漫画改",
      "number": "51"
    },
    {
      "label": "TV",
      "number": "50"
    },
    {
      "label": "后宫",
      "number": "41"
    },
    {
      "label": "漫改",
      "number": "39"
    },
    {
      "label": "2019",
      "number": "38"
    },
    {
      "label": "元永庆太郎",
      "number": "22"
    },
    {
      "label": "恋爱",
      "number": "14"
    },
    {
      "label": "日常",
      "number": "7"
    },
    {
      "label": "宅",
      "number": "6"
    },
    {
      "label": "元永慶太郎",
      "number": "6"
    },
    {
      "label": "搞笑",
      "number": "3"
    },
    {
      "label": "日本",
      "number": "3"
    },
    {
      "label": "日本动画",
      "number": "2"
    },
    {
      "label": "异世界",
      "number": "2"
    },
    {
      "label": "2018年4月",
      "number": "1"
    },
    {
      "label": "不到7分",
      "number": "1"
    }
  ],
  "score": {
    "global_score": "6.6",
    "score_chart": [
      {
        "label": "10",
        "count": "(3)"
      },
      {
        "label": "9",
        "count": "(5)"
      },
      {
        "label": "8",
        "count": "(42)"
      },
      {
        "label": "7",
        "count": "(126)"
      },
      {
        "label": "6",
        "count": "(78)"
      },
      {
        "label": "5",
        "count": "(26)"
      },
      {
        "label": "4",
        "count": "(11)"
      },
      {
        "label": "3",
        "count": "(0)"
      },
      {
        "label": "2",
        "count": "(2)"
      },
      {
        "label": "1",
        "count": "(1)"
      }
    ]
  },
  "summary": [
    "三次元（現実）の女性に興味が無い硬派なオタク、房伊田春人。ある日、大好きなアニメのヒロイン・ノーナの美少女フィギュアを購入したが、突然フィギュアのはずのノーナが動き出した！一人と一機（？）のドタバタ夫婦的生活、始まる！"
  ],
  "user_intros": [
    {
      "job": "主角",
      "name": "ノーナ / 诺娜",
      "cv": [
        "木下鈴奈"
      ]
    },
    {
      "job": "主角",
      "name": "房伊田春人 / 房伊田春人",
      "cv": [
        "羽多野渉"
      ]
    },
    {
      "job": "主角",
      "name": "ベルノア / 蓓儿诺雅",
      "cv": [
        "千本木彩花"
      ]
    },
    {
      "job": "主角",
      "name": "天乃原すばる / 天乃原昴",
      "cv": [
        "M・A・O"
      ]
    },
    {
      "job": "配角",
      "name": "オズマ",
      "cv": [
        "森川智之"
      ]
    },
    {
      "job": "配角",
      "name": "冠成次郎",
      "cv": [
        "河西健吾"
      ]
    },
    {
      "job": "配角",
      "name": "房伊田ミコト / 房伊田美琴",
      "cv": [
        "松田利冴"
      ]
    },
    {
      "job": "配角",
      "name": "クサビ",
      "cv": [
        "徳井青空"
      ]
    },
    {
      "job": "配角",
      "name": "リンドウ",
      "cv": [
        "篠原侑"
      ]
    }
  ],
  "complaints": [
    "A-（8.2）泪目，实在是太好看了。当你喜欢的二次元角色打破次元壁到现实世界你会怎么做，当然是选择和ta谈恋爱啦。当你也能穿越到你喜欢的二次元世界你会怎么做，当然是带着剧本闯世界啦。就是这种宅宅的幻想，实在太悲伤了，动画填补了我的幻想……不过穿越到现实世界的是手办小人，也有不一样的风趣~被几个二次元小人争风吃醋，开启惨烈修罗场，素敌~动画中各种整活与设定都挺有意思的，能和二次元角色在一起的美梦做做就得了……完结撒花感谢陪伴！",
    "复古感拉满，味儿很纯的阿宅动画",
    "创意挺有意思的、希望我的手办也能活过来",
    "真好。可爱。想买（然而看了一眼放送时间，",
    "figure动了",
    "创意很好，我的手办啥时候活过来？",
    "看完会心一笑，非常有意思 阿宅的想法感同身受 你可以说这故事只是毫无羞耻的宅男意淫，在幻想故事里尽情做自己想做的事，喜欢的手办活了每天一起生活  穿越到喜欢的动画自己改写结局 进入到喜欢的游戏和主人公一起冒险 和同是阿宅属性的游戏角色一起看动画玩游戏 编剧毫不羞耻地做了这一点",
    "创意虽好，但展开乏味。不停推出新的女角色来推进剧情，新鲜劲儿过了就没味儿了。以女主的动画展开结局，收尾一塌糊涂。福利有限，歌还行。",
    "6+",
    "其实还挺逗的。。"
  ],
  "comments": []
}