{
  "name": "劇場版∀ガンダムI 地球光",
  "info_box": {
    "中文名: ": "剧场版∀高达I 地球光",
    "话数: ": "1",
    "原作: ": [
      "矢立肇"
    ],
    "脚本: ": [
      "星山博之",
      "高橋哲子",
      "太田愛"
    ],
    "演出: ": [
      "鳥羽聡"
    ],
    "音乐: ": [
      "菅野よう子"
    ],
    "人物原案: ": [
      "安田朗"
    ],
    "色彩设计: ": [
      "笠森美代子"
    ],
    "作画监督: ": [
      "後藤雅巳",
      "中田栄治"
    ],
    "摄影监督: ": [
      "大神洋一"
    ],
    "原画: ": [
      "高瀬健一",
      "野館誠一",
      "川口栄夫"
    ],
    "动画检查: ": [
      "平出差知予"
    ],
    "剪辑: ": [
      "山森重之"
    ],
    "特效: ": [
      "長谷川敏生"
    ],
    "动画制作: ": [
      "サンライズ"
    ],
    "总导演: ": [
      "富野由悠季"
    ],
    "别名: ": "Turn A高达 剧场版 地球光",
    "上映年度: ": "2002年2月9日",
    "片长: ": "128分钟",
    "Copyright: ": "©創通・SUNRISE",
    "导演: ": "富野由悠季"
  },
  "attitude": [
    "169人想看",
    "360人看过",
    "6人在看",
    "26人搁置",
    "22人抛弃"
  ],
  "label": [
    {
      "label": "剧场版",
      "number": "91"
    },
    {
      "label": "高达",
      "number": "63"
    },
    {
      "label": "SUNRISE",
      "number": "56"
    },
    {
      "label": "富野由悠季",
      "number": "49"
    },
    {
      "label": "2002",
      "number": "26"
    },
    {
      "label": "菅野洋子",
      "number": "24"
    },
    {
      "label": "GUNDAM",
      "number": "23"
    },
    {
      "label": "萝卜",
      "number": "18"
    },
    {
      "label": "机战",
      "number": "13"
    },
    {
      "label": "科幻",
      "number": "13"
    },
    {
      "label": "原创",
      "number": "13"
    },
    {
      "label": "总集篇",
      "number": "6"
    },
    {
      "label": "日本",
      "number": "3"
    },
    {
      "label": "战争",
      "number": "3"
    },
    {
      "label": "动画",
      "number": "2"
    },
    {
      "label": "2002年",
      "number": "2"
    },
    {
      "label": "补番",
      "number": "2"
    },
    {
      "label": "菅野よう子",
      "number": "2"
    },
    {
      "label": "热血",
      "number": "2"
    },
    {
      "label": "サンライズ",
      "number": "2"
    },
    {
      "label": "日本动画",
      "number": "2"
    }
  ],
  "score": {
    "global_score": "7.2",
    "score_chart": [
      {
        "label": "10",
        "count": "(11)"
      },
      {
        "label": "9",
        "count": "(20)"
      },
      {
        "label": "8",
        "count": "(61)"
      },
      {
        "label": "7",
        "count": "(73)"
      },
      {
        "label": "6",
        "count": "(43)"
      },
      {
        "label": "5",
        "count": "(12)"
      },
      {
        "label": "4",
        "count": "(7)"
      },
      {
        "label": "3",
        "count": "(2)"
      },
      {
        "label": "2",
        "count": "(0)"
      },
      {
        "label": "1",
        "count": "(0)"
      }
    ]
  },
  "summary": [
    "∀GUNDAM又稱Turn-A GUNDAM，是於1999年為了慶祝GUNDAM系列誕生20週年而製作的一套TV版作品。由原作富野由悠季身任製作人。從1999年（平成11年）4月9日到2000年（平成12年）4月14日富士TV播放了全系列共50話。2002年在TV版内容再次編集的基礎上，日本又上映了兩部∀GUNDAM的動畫電影《地球光》和《月光蝶》。",
    "\r\n《地球光》（第1話〜第27話）"
  ],
  "user_intros": [
    {
      "job": "主角",
      "name": "ロラン・セアック / 罗兰·塞亚克",
      "cv": [
        "朴璐美"
      ]
    },
    {
      "job": "主角",
      "name": "キエル・ハイム / 姬艾尔·海姆",
      "cv": [
        "高橋理恵子"
      ]
    },
    {
      "job": "配角",
      "name": "ハリー・オード",
      "cv": [
        "稲田徹"
      ]
    },
    {
      "job": "配角",
      "name": "リリ・ボルジャーノ",
      "cv": [
        "小林愛"
      ]
    },
    {
      "job": "配角",
      "name": "ヤーニ・オビュス",
      "cv": [
        "桐本拓哉"
      ]
    },
    {
      "job": "配角",
      "name": "ジョゼフ・ヨット",
      "cv": [
        "佐藤せつじ"
      ]
    },
    {
      "job": "配角",
      "name": "ラダラム・クン",
      "cv": [
        "沢木郁也"
      ]
    },
    {
      "job": "配角",
      "name": "ヤコップ",
      "cv": [
        "宇垣秀成"
      ]
    },
    {
      "job": "配角",
      "name": "マリガン",
      "cv": [
        "堀内賢雄"
      ]
    }
  ],
  "complaints": [
    "虽说被剪成了骨架。但追加cut也有很多。音效也理所当然的比TV版丰富。作为特典来看还不错。",
    "（6.5/10）TV的1-27集的剧场总集篇，好好好富野你这么剪总集篇是吧。为了迎合剧场版的篇幅不删减剧本而去压榨内容，细节大量缩水后留下干瘪的大纲马不停蹄地往前赶（仿佛在看4倍速的TV），人物本就暗藏的情绪起伏被砍得更不成样子，部分混乱的群戏搅成一团麻，人物脑回路思考逻辑都被剪得跳断层了，中期节奏稍微缓和时才有了点原来的味道。要不是看过TV我可真要放弃思考了，难以想象从剧场版补turnA的观众得有多懵逼，许多能被称作“铺垫”的东西都被一带而过导致大部分桥段都很突兀，跟不上节奏估计看都看不明白势力分派。TV版重要的日常回基调非常平和，而剧场版近乎半数风格的丧失是对核心的背道而驰，反而让本就自说自话的冲突更为儿戏了。作画貌似略微改动但没啥本质区别，作为剧场版制作不太够格，不过菅野的配乐仍不错。",
    "总集",
    "温柔的光头",
    "一直很难GET到倒A的优点，但音乐的确很不错",
    "补标，不评分，tv版待重看。",
    "20230507:N年前看的TV，乍一看这剧场版居然有点不懂了，还是跳的太快了，特别是开胡子高达之前的大段剧情直接剪掉了。月球女王和大小姐贴贴可爱，可惜更可爱的二小姐戏份太少了剧场版里根本没体现出来。",
    "太赶了哥们儿。新曲好听。",
    "一反 UC 纪元的开战理由，激进军民高歌民族主义赤目相对，温柔贤明的领主们艰难地控制局面。黑皮且去性别特征的主角设定表达着当时导演对新一代的祝愿吧，结果放今天大概率被喷政治正确。地月相隔的两个女王，不知道有没有受线粒体 DNA 母系遗传（天海佑希西藏寻亲）的影响。",
    "高达剧场版，超级快速的剪辑"
  ],
  "comments": []
}