{
  "name": "ポケットモンスター めざせポケモンマスター",
  "info_box": {
    "中文名: ": "宝可梦 旅途 目标是宝可梦大师",
    "话数: ": "11",
    "放送开始: ": "2023年1月13日",
    "放送星期: ": "星期五",
    "导演: ": [
      "冨安大貴"
    ],
    "脚本: ": [
      "米村正二",
      "冨岡淳広"
    ],
    "分镜: ": [
      "中田誠",
      "尼野浩正",
      "浅田裕二",
      "齋藤徳明",
      "森山愛弓"
    ],
    "演出: ": [
      "上野史博",
      "小柴純弥",
      "向山鶴美",
      "浅田裕二",
      "森山愛弓"
    ],
    "音乐: ": [
      "林ゆうき"
    ],
    "人物设定: ": [
      "安田周平",
      "林千尋"
    ],
    "系列构成: ": [
      "冨岡淳広"
    ],
    "美术监督: ": [
      "武藤正敏"
    ],
    "色彩设计: ": [
      "吉野記通"
    ],
    "总作画监督: ": [
      "山崎玲愛",
      "伊藤京子",
      "安田周平"
    ],
    "作画监督: ": [
      "篠原隆",
      "安田周平",
      "倉員千晶",
      "広岡トシヒト",
      "岩根雅明",
      "伊藤京子"
    ],
    "摄影监督: ": [
      "鈴木大倫"
    ],
    "原画: ": [
      "広岡トシヒト",
      "大原和男",
      "篠原隆",
      "木下麗江",
      "岩根雅明",
      "森中正春",
      "松坂定俊",
      "一石小百合",
      "村司晃英",
      "崎山知明",
      "岩井田夏帆",
      "江口晶沙",
      "松原徳弘",
      "野津美智子",
      "結城明宏",
      "伊藤京子"
    ],
    "第二原画: ": [
      "森山愛弓",
      "何金龙"
    ],
    "动画检查: ": [
      "大山愛子"
    ],
    "原案: ": [
      "杉森建",
      "田尻智",
      "増田順一"
    ],
    "主题歌编曲: ": [
      "渡部チェル"
    ],
    "主题歌作曲: ": [
      "たなかひろかず"
    ],
    "主题歌作词: ": [
      "戸田昭吾"
    ],
    "主题歌演出: ": [
      "松本梨香",
      "石塚運昇"
    ],
    "製作: ": [
      "テレビ東京",
      "テレビ東京メディアネット",
      "小学館集英社プロダクション"
    ],
    "音响监督: ": [
      "三間雅文"
    ],
    "制作协调: ": [
      "坂本鼓太郎"
    ],
    "音乐制作: ": [
      "テレビ東京ミュージック"
    ],
    "动画制作: ": [
      "OLM"
    ],
    "总导演: ": [
      "湯山邦彦"
    ],
    "动画制片人: ": [
      "加藤浩幸"
    ],
    "别名: ": "Pocket Monsters: Mezase Pokémon Master",
    "官方网站: ": "https://www.tv-tokyo.co.jp/anime/pocketmonster/",
    "播放电视台: ": "テレビ東京系",
    "播放结束: ": "2023年3月24日",
    "Copyright: ": "©Nintendo･Creatures･GAME FREAK･TV Tokyo･ShoPro･JR Kikaku ©Pokémon"
  },
  "attitude": [
    "184人想看",
    "555人看过",
    "128人在看",
    "51人搁置",
    "48人抛弃"
  ],
  "label": [
    {
      "label": "TV",
      "number": "112"
    },
    {
      "label": "宝可梦",
      "number": "108"
    },
    {
      "label": "2023年1月",
      "number": "84"
    },
    {
      "label": "2023",
      "number": "63"
    },
    {
      "label": "OLM",
      "number": "60"
    },
    {
      "label": "童年",
      "number": "58"
    },
    {
      "label": "游戏改",
      "number": "55"
    },
    {
      "label": "精灵宝可梦",
      "number": "51"
    },
    {
      "label": "原创",
      "number": "27"
    },
    {
      "label": "皮卡丘",
      "number": "20"
    },
    {
      "label": "pokemon",
      "number": "19"
    },
    {
      "label": "神奇宝贝",
      "number": "15"
    },
    {
      "label": "青春",
      "number": "6"
    },
    {
      "label": "日常",
      "number": "4"
    },
    {
      "label": "完结篇",
      "number": "4"
    },
    {
      "label": "宠物小精灵",
      "number": "3"
    },
    {
      "label": "日本动画",
      "number": "3"
    },
    {
      "label": "季番",
      "number": "2"
    },
    {
      "label": "大长篇",
      "number": "2"
    },
    {
      "label": "剧集",
      "number": "2"
    },
    {
      "label": "OLMTEAMOTA",
      "number": "1"
    },
    {
      "label": "长剧集",
      "number": "1"
    }
  ],
  "score": {
    "global_score": "7.0",
    "score_chart": [
      {
        "label": "10",
        "count": "(38)"
      },
      {
        "label": "9",
        "count": "(21)"
      },
      {
        "label": "8",
        "count": "(66)"
      },
      {
        "label": "7",
        "count": "(145)"
      },
      {
        "label": "6",
        "count": "(95)"
      },
      {
        "label": "5",
        "count": "(34)"
      },
      {
        "label": "4",
        "count": "(9)"
      },
      {
        "label": "3",
        "count": "(2)"
      },
      {
        "label": "2",
        "count": "(2)"
      },
      {
        "label": "1",
        "count": "(5)"
      }
    ]
  },
  "summary": [
    "1997 年 4 月、サトシとピカチュウはマサラタウンから旅立ち、「ポケットモンスター」の世界へと踏み出しました。たくさんの仲間たちと出会い、バトルする中でサトシがずっと変わらず目指してきたのは、あこがれの「ポケモンマスター」になること。",
    "\r\n",
    "\r\n2023 年 1 月 13 日(金)から放送する「ポケットモンスター めざせポケモンマスター」では、その見果てぬ夢に向かっていくサトシとピカチュウの冒険が 全 11 話(予定)に渡って描かれます。",
    "\r\n",
    "\r\n放送では、かつて共に旅をしたカスミとタケシのほか、サトシが各地方で強い絆を結びゲットしたポケモンたちが登場。ワクワクと感動がいっぱいの冒険をさらに盛り上げます。"
  ],
  "user_intros": [
    {
      "job": "主角",
      "name": "サトシ / 小智",
      "cv": [
        "松本梨香"
      ]
    },
    {
      "job": "主角",
      "name": "サトシのピカチュウ / 小智的皮卡丘",
      "cv": []
    },
    {
      "job": "主角",
      "name": "カスミ / 小霞",
      "cv": []
    },
    {
      "job": "主角",
      "name": "タケシ / 小刚",
      "cv": []
    },
    {
      "job": "配角",
      "name": "デント / 天桐",
      "cv": [
        "宮野真守"
      ]
    },
    {
      "job": "配角",
      "name": "ジョーイ / 乔伊",
      "cv": [
        "真堂圭"
      ]
    },
    {
      "job": "配角",
      "name": "ジュンサー / 君莎",
      "cv": [
        "清水理沙"
      ]
    },
    {
      "job": "配角",
      "name": "ニャース / 喵喵",
      "cv": []
    },
    {
      "job": "配角",
      "name": "ムサシ / 武藏",
      "cv": []
    }
  ],
  "complaints": [
    "也就剩个情怀了",
    "这碗青春断头饭 满满都是遗憾 可怜小智这么多年竟然是在烂的一塌糊涂的旅途夺冠 害……",
    "不知道该怎么去形容宝可梦大师，要我说的话，大概就是他们给智爷和皮神最后的温柔吧，都结束了，我看了10多年的宝可梦，虽远不及25年之久，但也由衷觉得就这么结束，还是不甘心啊，看到小智和伙伴再次组队旅行，以前的宝可梦相继出场，很多话到了嘴边也不知怎么开口，最后我只想说一句，非常感谢……",
    "情怀拉满了",
    "想给一个情怀分依旧做不到，旅途的最后依旧是让人失望的",
    "前三集拉满，结局无法接受。我智爷的最后一舞就这么结束了！",
    "我要对陪伴了我这么久的小智说再见了",
    "我不管，傻东西的最后一舞，必须满分",
    "做的不行其实，卖情怀占绝大多数，挺失望的",
    "再見了小智&皮卡丘，感謝你們20多年的陪伴"
  ],
  "comments": [
    "原文全部来自松本梨香本人推特 个人翻译\r\n————————————————————————\r\n人生は、嬉しい方の涙探し。みんなからの暖かいメッセージにずっと泣かされっぱなしです。本当に心からありがとう♪♪♪まるごと、ぜーんぶ全てに感謝の気持ちで胸 ... ",
    "人若因我辱骂你们，迫害你们，捏造各样坏话毁谤你们，你们就有福了！无论其他人如何打分，我的打分永远是最高点。 "
  ]
}