{
  "name": "いぬかみっ! THE MOVIE 特命霊的捜査官・仮名史郎っ!",
  "info_box": {
    "中文名: ": "犬神 剧场版",
    "话数: ": "1",
    "原作: ": [
      "有沢まみず"
    ],
    "导演: ": [
      "草川啓造"
    ],
    "人物原案: ": [
      "若月神無"
    ],
    "原画: ": [
      "田中ちゆき"
    ],
    "特效: ": [
      "福田直征"
    ],
    "制作: ": [
      "Seven Arcs"
    ],
    "动画制作: ": [
      "Seven Arcs"
    ],
    "上映年度: ": "2007年4月21日",
    "片长: ": "30分"
  },
  "attitude": [
    "74人想看",
    "169人看过",
    "1人在看",
    "7人搁置",
    "7人抛弃"
  ],
  "label": [
    {
      "label": "剧场版",
      "number": "55"
    },
    {
      "label": "搞笑",
      "number": "26"
    },
    {
      "label": "轻小说改",
      "number": "16"
    },
    {
      "label": "SevenArcs",
      "number": "14"
    },
    {
      "label": "2007",
      "number": "13"
    },
    {
      "label": "堀江由衣",
      "number": "12"
    },
    {
      "label": "福山潤",
      "number": "7"
    },
    {
      "label": "节操",
      "number": "6"
    },
    {
      "label": "奇幻",
      "number": "4"
    },
    {
      "label": "后宫",
      "number": "4"
    },
    {
      "label": "2007年",
      "number": "4"
    },
    {
      "label": "小说改",
      "number": "3"
    },
    {
      "label": "SEVEN・ARCS",
      "number": "3"
    },
    {
      "label": "轻改",
      "number": "2"
    },
    {
      "label": "神魔",
      "number": "2"
    },
    {
      "label": "2007年4月",
      "number": "2"
    },
    {
      "label": "绅士",
      "number": "2"
    },
    {
      "label": "恋爱",
      "number": "2"
    },
    {
      "label": "日本动画",
      "number": "2"
    },
    {
      "label": "アニメ映画",
      "number": "1"
    },
    {
      "label": "卖肉",
      "number": "1"
    }
  ],
  "score": {
    "global_score": "6.3",
    "score_chart": [
      {
        "label": "10",
        "count": "(0)"
      },
      {
        "label": "9",
        "count": "(1)"
      },
      {
        "label": "8",
        "count": "(7)"
      },
      {
        "label": "7",
        "count": "(33)"
      },
      {
        "label": "6",
        "count": "(32)"
      },
      {
        "label": "5",
        "count": "(9)"
      },
      {
        "label": "4",
        "count": "(4)"
      },
      {
        "label": "3",
        "count": "(1)"
      },
      {
        "label": "2",
        "count": "(0)"
      },
      {
        "label": "1",
        "count": "(0)"
      }
    ]
  },
  "summary": [
    "『いぬかみっ! THE MOVIE 特命霊的捜査官・仮名史郎っ!』のタイトルで電撃文庫ムービーフェスティバルとして2007年4月21日から『灼眼のシャナ』と『キノの旅』同時上映で公開。TVシリーズにて、放送上の関係でほとんどできなかった女性キャラのお色気シーンを多く取り入れている。映像化は、本作が現在のところ最後となっている。"
  ],
  "user_intros": [
    {
      "job": "主角",
      "name": "ようこ / 阳子",
      "cv": []
    }
  ],
  "complaints": [
    "好多neta 还挺乐的",
    "这个剧场版虽然看的时候人名都不记得了，但还是感受到了无主线导致变态浓度再次直线上升。还玩了奈叶、凉宫、蜻蜓队长的梗，作者老恶心宅男了（好吧其实对标那会应该都是当红剧集。",
    "一群变态实在是辣眼睛要瞎了！！26分怎么条目的标的是30分？剧情还算有趣，开头没一会妹子们脱衣杀必死，接着假名莫名挂了男主想去丧会但被一群k组织阻止，他们还逮捕所有变态，k组织原来是因为假名厌恶变态的愿望产生的，主角团和他们战斗但寡不敌众，他们合体变成大萝卜最后男主用大青蛙雕像干掉了接着假名就醒来没一会和男主见面就全裸搞基辣瞎眼睛！！！",
    "neta了不少萝卜特摄梗，看笑了",
    "不愧是剧场版 经费很足",
    "看得挺开心",
    "裸王强无敌 男人变态有什么错 比TV制作要好不少",
    "好！",
    "我到底看了什么。。。",
    "剧场版作画真好，TV有这一半质量就好了"
  ],
  "comments": []
}