{
  "name": "名探偵コナン",
  "info_box": {
    "中文名: ": "名侦探柯南",
    "话数: ": "*",
    "放送开始: ": "1996年1月8日",
    "放送星期: ": "星期六（#530-）、星期一（#1-#529）",
    "原作: ": [
      "青山剛昌"
    ],
    "导演: ": [
      "こだま兼嗣",
      "山本泰一郎",
      "佐藤真人",
      "於地紘仁",
      "山本泰一郎",
      "於地紘仁",
      "山本泰一郎",
      "山本泰一郎",
      "鎌仲史陽"
    ],
    "脚本: ": [
      "古内一成",
      "宮下隼一",
      "井上敏樹",
      "日暮裕一",
      "平野靖士",
      "於地紘仁",
      "扇澤延男",
      "まさきひろ",
      "金子裕",
      "島田満",
      "桜井正明",
      "森下直",
      "三上幸四郎",
      "村川康敏",
      "望月武",
      "浦沢義雄",
      "石川あさみ",
      "前川淳",
      "鎌仲史陽",
      "大倉崇裕",
      "飯岡順一",
      "辻真先",
      "稲本達郎",
      "柏原寛司",
      "山田豊",
      "岡部優子",
      "大和屋暁",
      "大川俊道",
      "櫻井武晴"
    ],
    "分镜: ": [
      "こだま兼嗣",
      "佐藤真人",
      "於地紘仁",
      "松浦錠平",
      "松園公",
      "山本泰一郎",
      "野上和男",
      "櫻井美知代",
      "荻原露光",
      "佐々木純人",
      "長尾粛",
      "永岡智佳",
      "芦沢剛史",
      "鈴木吉男",
      "加瀬充子",
      "宮地昌幸",
      "影山楙倫",
      "土屋日",
      "黒田晃一郎",
      "岩間貴",
      "佐々木皓一",
      "遠藤克己",
      "渡辺純央",
      "西澤晋",
      "喜多幡徹",
      "原田奈々",
      "吉村章",
      "満仲勧",
      "許平康",
      "横田和善",
      "小林一三",
      "金﨑貴臣",
      "鈴木拓磨",
      "鎌仲史陽",
      "京極尚彦",
      "高木啓明",
      "奥脇雅晴",
      "名村英敏",
      "辻初樹",
      "峯友則"
    ],
    "演出: ": [
      "こだま兼嗣",
      "佐藤真人",
      "於地紘仁",
      "松浦錠平",
      "野上和男",
      "山本泰一郎",
      "鈴木吉男",
      "原田奈々",
      "久保山英一",
      "荻原露光",
      "鎌仲史陽",
      "関谷真実子",
      "斉藤啓也",
      "新子太一",
      "古田丈司",
      "高田昌宏",
      "桑原智",
      "依田正彦",
      "藤野陽介",
      "谷澤篤金",
      "茉田哲明",
      "浅見松雄",
      "内田祐司",
      "菅井嘉浩",
      "元永慶太郎",
      "進藤陽平",
      "南康宏",
      "和泉志郎",
      "麦野アイス",
      "篠原俊哉",
      "京極尚彦",
      "秋山宏",
      "石川敏浩",
      "喜多幡徹",
      "山崎正和",
      "佐々木純人",
      "齋藤徳明",
      "谷田部勝義",
      "安部祐二郎",
      "矢野孝典",
      "福島陽子",
      "堀内バロン",
      "向山鶴美",
      "野崎真代",
      "河原龍太",
      "静野孔文",
      "山口美浩",
      "長岡義孝",
      "吉村章",
      "土屋日",
      "山口頼房",
      "池田智美",
      "西村大樹",
      "佐々木皓一",
      "早瀬真紀子",
      "長尾粛",
      "横田和善",
      "田中智也",
      "佐藤育郎",
      "土屋康郎",
      "黒田晃一郎",
      "高木啓明"
    ],
    "音乐: ": [
      "大野克夫"
    ],
    "人物设定: ": [
      "須藤昌朋",
      "とみながまり",
      "須藤昌朋",
      "山中純子",
      "須藤昌朋",
      "須藤昌朋",
      "牟田清司",
      "須藤昌朋",
      "須藤昌朋",
      "岩井伸之",
      "須藤昌朋"
    ],
    "系列构成: ": [
      "飯岡順一"
    ],
    "美术监督: ": [
      "渋谷幸弘",
      "加藤靖忠",
      "谷村心一",
      "東潤一"
    ],
    "色彩设计: ": [
      "平山礼子",
      "中尾総子",
      "海鋒重信",
      "中尾総子"
    ],
    "总作画监督: ": [
      "牟田清司",
      "とみながまり"
    ],
    "作画监督: ": [
      "柳瀬譲二",
      "谷圭司",
      "斎藤新明",
      "たないあやこ",
      "崔骏翔",
      "垪和等",
      "能條理行",
      "田中紀衣",
      "広中千恵美",
      "山崎展義",
      "南伸一郎",
      "秋山由樹子",
      "神谷友美",
      "粟井重紀",
      "小笠原理恵",
      "森田実",
      "张益",
      "大塚美登理",
      "山本道隆",
      "アベ正己",
      "杨国福",
      "黄凤",
      "熊田亜輝",
      "佐々木恵子",
      "石井ゆみこ",
      "陈洁琼",
      "凌雪春",
      "山村俊了",
      "胡威",
      "山崎正和",
      "宮井加奈",
      "都竹隆治",
      "朴旲烈",
      "菅野智之",
      "小林一三",
      "石井繁",
      "牟田清司",
      "鈴木克",
      "渡辺章",
      "宍戸久美子",
      "藤岡真紀",
      "鈴木裕輔",
      "清水勝祐",
      "山中純子",
      "青井清年",
      "高谷浩利",
      "大河原晴男",
      "依田正彦",
      "杉本道明",
      "堀内博之",
      "石野聡",
      "山本天志",
      "福永智子",
      "齋藤樹里",
      "西田亜沙子",
      "はしもとかつみ",
      "鈴木伸一",
      "川島明子",
      "吉見京子",
      "岩井伸之",
      "今泉竜太",
      "小林ゆかり",
      "増永麗",
      "古佐小吉重",
      "井元愛夕",
      "小林勝利",
      "松本朋之",
      "青野厚司",
      "野村美織",
      "大島美和",
      "杉藤さゆり",
      "平林孝",
      "田中保",
      "陈晓岚",
      "原田峰文",
      "武内啓",
      "糸島雅彦",
      "永野美春",
      "今田茜",
      "村上勉",
      "須藤昌朋",
      "大友健一",
      "西山忍",
      "田中美穂",
      "松尾真彦",
      "谷口守泰",
      "橋本正則",
      "本橋秀之",
      "花輪美幸",
      "渡部ゆかり",
      "山沢実"
    ],
    "摄影监督: ": [
      "野村隆",
      "小川隆久",
      "小川隆久"
    ],
    "监修: ": [
      "諏訪道彦"
    ],
    "原画: ": [
      "中村和久",
      "高橋晃",
      "佐久間信一",
      "飯飼一幸",
      "高橋紀子",
      "石野聡",
      "高谷浩利",
      "細居美恵子",
      "増田雄一郎",
      "马兰",
      "龚豪",
      "加藤はつえ",
      "湖川友謙",
      "袁東",
      "鈴木FALCO",
      "小美野雅彦",
      "懸田扇子",
      "西村貴世",
      "楠田博樹",
      "桑原愛",
      "吉毅",
      "櫻井梨恵子",
      "時永宜幸",
      "寺尾洋之",
      "柴晨钟",
      "敬维",
      "松本澄子",
      "村田理",
      "岡真里子",
      "飯塚晴子",
      "佐々木純人",
      "なかじまちゅうじ",
      "寺岡巌",
      "田中ちゆき",
      "酒井啓史",
      "小川みずえ",
      "依田正彦",
      "田中紀衣",
      "HSM",
      "加々美高浩",
      "朱暁",
      "樫山聡之",
      "大木良一",
      "山川浩臣",
      "小林冬至生",
      "平山英嗣",
      "石川てつや",
      "芳尾英明",
      "吉川博明",
      "一居一平",
      "仇振华",
      "和田高明",
      "神北小毬",
      "糸島雅彦",
      "堀内博之",
      "崔骏翔",
      "路夏生",
      "菅野芳弘"
    ],
    "第二原画: ": [
      "神北小毬",
      "松井怜"
    ],
    "动画检查: ": [
      "江野沢柚美",
      "平山英嗣"
    ],
    "背景美术: ": [
      "スタジオ・イースター"
    ],
    "色彩指定: ": [
      "平山礼子"
    ],
    "剪辑: ": [
      "岡田輝満"
    ],
    "主题歌演出: ": [
      "倉木麻衣",
      "小松未歩",
      "ZARD",
      "↑THE HIGH-LOWS↓"
    ],
    "插入歌演出: ": [
      "↑THE HIGH-LOWS↓"
    ],
    "企画: ": [
      "諏訪道彦"
    ],
    "音响监督: ": [
      "小林克良",
      "浦上靖夫",
      "浦上靖夫",
      "井澤基",
      "井澤基",
      "浦上靖夫",
      "井澤基",
      "浦上靖夫",
      "浦上靖夫",
      "浦上慶子",
      "浦上靖之",
      "浦上慶子"
    ],
    "音效: ": [
      "横山正和",
      "横山亜紀"
    ],
    "特效: ": [
      "浦大器",
      "西村龍徳"
    ],
    "补间动画: ": [
      "沈暁陽",
      "桑原愛",
      "清水美友紀",
      "丸山修二",
      "阿部望",
      "HSM",
      "吉野恵子",
      "松井怜",
      "小島智加",
      "岡田万衣子"
    ],
    "制片人: ": [
      "諏訪道彦",
      "吉岡昌仁"
    ],
    "总制片人: ": [
      "諏訪道彦",
      "永井幸治",
      "吉岡昌仁",
      "石山桂一"
    ],
    "制作: ": [
      "読売テレビ",
      "東京ムービー",
      "トムス・エンタテインメント",
      "キョクイチ東京ムービー"
    ],
    "动画制作: ": [
      "東京ムービー",
      "トムス・エンタテインメント",
      "V1Studio"
    ],
    "副导演: ": [
      "佐藤真人"
    ],
    "OP・ED 分镜: ": [
      "ほりうちゆうや",
      "安部祐二郎",
      "満仲勧",
      "松園公",
      "重原克也",
      "鈴木利正",
      "平野俊貴",
      "加瀬充子",
      "於地紘仁",
      "小坂知",
      "山本泰一郎",
      "神村幸子",
      "佐藤真人",
      "静野孔文",
      "瀬下寛之",
      "野上和男",
      "寺岡巌",
      "金井次郎",
      "こだま兼嗣",
      "鎌仲史陽",
      "高谷浩利"
    ],
    "总导演: ": [
      "こだま兼嗣"
    ],
    "制作协力: ": [
      "ゆめ太カンパニー（旧）",
      "アクタス",
      "アイムーヴ",
      "ビッグ・バン",
      "Triple A",
      "スタジオケルマディック",
      "フロントライン",
      "マジックバス",
      "V1Studio",
      "ダンガンピクチャーズ",
      "アゼータ・ピクチャーズ",
      "A.P.P.P.",
      "円谷プロダクション",
      "南町奉行所",
      "葦プロダクション",
      "スタジオイゼナ"
    ],
    "官方网站: ": "http://www.ytv.co.jp/conan/",
    "播放电视台: ": "読売テレビ",
    "其他电视台: ": "日本テレビ系列局",
    "助理制片人: ": "小学館：浅井認（#333-#749）→近藤秀峰（#750-）",
    "动画制片人: ": "山川剛史（#530-#601）"
  },
  "attitude": [
    "661人想看",
    "6103人看过",
    "6773人在看",
    "2359人搁置",
    "725人抛弃"
  ],
  "label": [
    {
      "label": "柯南",
      "number": "2289"
    },
    {
      "label": "万年小学生",
      "number": "1923"
    },
    {
      "label": "名探偵コナン",
      "number": "1613"
    },
    {
      "label": "推理",
      "number": "1464"
    },
    {
      "label": "青山刚昌",
      "number": "1103"
    },
    {
      "label": "-完结摇摇无指日……",
      "number": "1022"
    },
    {
      "label": "看到哪了",
      "number": "664"
    },
    {
      "label": "TV",
      "number": "576"
    },
    {
      "label": "悬疑",
      "number": "548"
    },
    {
      "label": "坑",
      "number": "346"
    },
    {
      "label": "1996",
      "number": "237"
    },
    {
      "label": "童年",
      "number": "159"
    },
    {
      "label": "漫画改",
      "number": "155"
    },
    {
      "label": "漫改",
      "number": "87"
    },
    {
      "label": "名侦探柯南",
      "number": "83"
    },
    {
      "label": "TMS",
      "number": "71"
    },
    {
      "label": "长篇",
      "number": "42"
    },
    {
      "label": "恋爱",
      "number": "26"
    },
    {
      "label": "经典",
      "number": "24"
    },
    {
      "label": "山口胜平",
      "number": "23"
    },
    {
      "label": "日本",
      "number": "22"
    },
    {
      "label": "动画",
      "number": "17"
    },
    {
      "label": "90年代",
      "number": "15"
    }
  ],
  "score": {
    "global_score": "7.6",
    "score_chart": [
      {
        "label": "10",
        "count": "(859)"
      },
      {
        "label": "9",
        "count": "(877)"
      },
      {
        "label": "8",
        "count": "(2232)"
      },
      {
        "label": "7",
        "count": "(2357)"
      },
      {
        "label": "6",
        "count": "(912)"
      },
      {
        "label": "5",
        "count": "(261)"
      },
      {
        "label": "4",
        "count": "(49)"
      },
      {
        "label": "3",
        "count": "(18)"
      },
      {
        "label": "2",
        "count": "(7)"
      },
      {
        "label": "1",
        "count": "(23)"
      }
    ]
  },
  "summary": [
    "主角工藤新一原本是一位颇具名声的高中生侦探，在目击黑暗组织的地下交易后，正准备追踪时却被突袭击昏，并被灌下代号为“APTX4869”（アポトキシン4869）的不明药物。后来虽然幸免于死，但身体就此缩小为小学时期的模样。之后他化名为江户川柯南，在邻居阿笠博士的建议下，寄住在女友毛利兰的父亲—侦探毛利小五郎家中，继续秘密从事追查黑暗组织的工作，并私下探寻获得解药的管道，希望能够恢复原来新一的样貌。与此同时，柯南凭着自己的推理天份，配合阿笠博士为他发明的道具，帮助毛利小五郎成为出名的大侦探。故事内容当中穿插许多爱情、友情、犯罪、背叛、复仇等情节。"
  ],
  "user_intros": [
    {
      "job": "主角",
      "name": "灰原哀 / 灰原哀",
      "cv": [
        "林原めぐみ"
      ]
    },
    {
      "job": "主角",
      "name": "江戸川コナン / 江户川柯南",
      "cv": [
        "高山みなみ"
      ]
    },
    {
      "job": "主角",
      "name": "工藤新一 / 工藤新一",
      "cv": [
        "山口勝平",
        "高山みなみ"
      ]
    },
    {
      "job": "主角",
      "name": "毛利蘭 / 毛利兰",
      "cv": [
        "山崎和佳奈"
      ]
    },
    {
      "job": "主角",
      "name": "毛利小五郎 / 毛利小五郎",
      "cv": [
        "小山力也",
        "神谷明"
      ]
    },
    {
      "job": "配角",
      "name": "阿笠博士 / 阿笠博士",
      "cv": [
        "緒方賢一",
        "田中一成"
      ]
    },
    {
      "job": "配角",
      "name": "吉田歩美 / 吉田步美",
      "cv": [
        "岩居由希子"
      ]
    },
    {
      "job": "配角",
      "name": "少年探偵団 / 少年偵探團",
      "cv": []
    },
    {
      "job": "配角",
      "name": "円谷光彦 / 圆谷光彦",
      "cv": [
        "大谷育江"
      ]
    }
  ],
  "complaints": [
    "这动画只能在无聊时用来图一乐，不适合连续看。跳着看了一百多集，套路已经完全摸清了。每个案件都很短，前期给的调查时间不够多，柯南遇到瓶颈时也都是靠运气发现的突破点，很多时候还安排得特别刻意。我小时候没看过，没有童年滤镜，看柯南也是完全冲着推理去的，在我看来这动画太一般了。",
    "前面几百集很好，越到后面画风和剧集质量都直线下滑也没再追了。",
    "推荐看的原因是纵使后期的剧情很弱智，但是并不妨碍在吃饭的时候看上一集消磨时光。仅仅是听上声音，小时候那种端着饭碗看电视的感觉就来了",
    "以前是真还不错的，现在纯粹是为了更新而更新",
    "后面烂的不想看，前面好看又嫌少。",
    "制作不被重视，持续用名场面充数卖情怀，你是懂怎么薄利多销的",
    "虽然只是轻度推理，但却是我的推理启蒙",
    "ep0001-0224，シーズン26 (2021年)-",
    "柯南还可以的",
    "原创剧集越来越不行了"
  ],
  "comments": [
    "大家好，本文章我自己总结的毛利兰在《名侦探柯南》TV动画中拯救的角色和制服的犯人（包含漫改和动画原创），目的是让更多的观众了解毛利兰。如果我有写错或者遗漏的地方，欢迎各位朋友指正或补充，感谢。\r\n\r\n1. 【漫改】原版第2话（国内拆分版第2话） 董事长千金绑架事件\r\n\r\n毛 ... ",
    "——工藤新一（江户川柯南）的择偶观：对异性不感兴趣，但原则上是毛利兰。\r\n\r\n从小二就开始看柯南了，印象比较深的是当时爱奇艺的长评区，那会新兰和柯哀的争斗就开始了。\r\n我本身是一直不站CP的，但是随着看柯南次数增加（主要是看前700集左右），我开始喜欢并且向往新兰之间的感情 ... ",
    "最近在回看柯南，发现里面的过客都好感人，岛袋君惠，吉野绫花，日向幸，森村爱子，青野木亮一的母亲，芙纱绘，鼹鼠星人和他的妹妹，香取茜，有森旅馆的经理和他的弟弟、还有厨师子门忍，蓝川冬矢，古川浩二和他姐姐、女仆町田梓，远野百合子和永井修平，真中大二郎，香阪夏美，新名香保里，鸟光 ... ",
    "看看 ",
    "1.没像海贼一样给9是因为低质量散集过多，早期的散集（前300）要么吓死个人（图书馆，蓝色古堡，雾天狗），要么手法高超（诅咒假面），要么悬疑爆棚（20年后的杀机），但后期就不太行了。（当然这也是没有办法）\r\n2.主线剧情10分无疑\r\n3.剧场版个人最喜欢的几部：世纪末，贝克街，倒计时，遇难船\r\n4.世纪 ... "
  ]
}