{
  "name": "STAND BY ME ドラえもん",
  "info_box": {
    "中文名: ": "哆啦A梦：伴我同行",
    "话数: ": "1",
    "原作: ": [
      "藤子・F・不二雄"
    ],
    "导演: ": [
      "八木竜一",
      "山崎貴"
    ],
    "脚本: ": [
      "山崎貴"
    ],
    "音乐: ": [
      "佐藤直紀"
    ],
    "主题歌编曲: ": [
      "秦基博",
      "皆川真人"
    ],
    "主题歌作曲: ": [
      "秦基博"
    ],
    "主题歌作词: ": [
      "秦基博"
    ],
    "主题歌演出: ": [
      "秦基博"
    ],
    "製作: ": [
      "大倉俊輔"
    ],
    "执行制片人: ": [
      "梅澤道彦"
    ],
    "制片人: ": [
      "岡田麻衣子"
    ],
    "制作: ": [
      "シンエイ動画",
      "小学館",
      "テレビ朝日",
      "小学館",
      "東宝",
      "電通",
      "白組",
      "ロボット",
      "朝日放送テレビ"
    ],
    "动画制作: ": [
      "シンエイ動画",
      "ロボット",
      "白組"
    ],
    "3DCG: ": [
      "天井和文"
    ],
    "上映年度: ": "2014年8月8日",
    "片长: ": "95分钟",
    "官方网站: ": "http://doraemon-3d.com/",
    "制作协力: ": "藤子プロ、阿部秀司事務所",
    "配给: ": "東宝"
  },
  "attitude": [
    "220人想看",
    "3610人看过",
    "8人在看",
    "28人搁置",
    "25人抛弃"
  ],
  "label": [
    {
      "label": "剧场版",
      "number": "717"
    },
    {
      "label": "哆啦A梦",
      "number": "498"
    },
    {
      "label": "3D",
      "number": "308"
    },
    {
      "label": "2014",
      "number": "296"
    },
    {
      "label": "童年",
      "number": "283"
    },
    {
      "label": "治愈",
      "number": "218"
    },
    {
      "label": "漫画改",
      "number": "165"
    },
    {
      "label": "SHIN-EI",
      "number": "91"
    },
    {
      "label": "シンエイ動画",
      "number": "67"
    },
    {
      "label": "白组",
      "number": "66"
    },
    {
      "label": "映画",
      "number": "49"
    },
    {
      "label": "漫改",
      "number": "37"
    },
    {
      "label": "科幻",
      "number": "16"
    },
    {
      "label": "2014年",
      "number": "13"
    },
    {
      "label": "搞笑",
      "number": "12"
    },
    {
      "label": "日本",
      "number": "12"
    },
    {
      "label": "动画电影",
      "number": "11"
    },
    {
      "label": "电影",
      "number": "10"
    },
    {
      "label": "恋爱",
      "number": "7"
    },
    {
      "label": "动画",
      "number": "7"
    },
    {
      "label": "劇場版",
      "number": "7"
    },
    {
      "label": "日本动画",
      "number": "6"
    },
    {
      "label": "日常",
      "number": "6"
    }
  ],
  "score": {
    "global_score": "7.3",
    "score_chart": [
      {
        "label": "10",
        "count": "(101)"
      },
      {
        "label": "9",
        "count": "(140)"
      },
      {
        "label": "8",
        "count": "(758)"
      },
      {
        "label": "7",
        "count": "(852)"
      },
      {
        "label": "6",
        "count": "(313)"
      },
      {
        "label": "5",
        "count": "(70)"
      },
      {
        "label": "4",
        "count": "(27)"
      },
      {
        "label": "3",
        "count": "(5)"
      },
      {
        "label": "2",
        "count": "(3)"
      },
      {
        "label": "1",
        "count": "(5)"
      }
    ]
  },
  "summary": [
    "为了什么都做不来的野比大雄，22 世纪的玄孙野比世修送了猫型机器人──哆啦A梦来现代。",
    "\r\n笨笨的野比大雄原本自己开了间公司，但很不幸的倒闭，之后剩下了一屁股债务，子孙们吃了莫大的苦。于是，野比世修才打算送哆啦A梦到现代，打算改变大雄的未来，并且为哆啦A梦设定了完成程式，如果野比大雄不幸福的话，哆啦A梦就不能回22世纪。",
    "\r\n哆啦A梦于是开始勉勉强强的协助野比大雄的日常生活。虽然刚开始不太习惯，但两个人的关系也日渐变的紧密。得知野比大雄的梦想是打算与梦中情人的同班同学源静香结婚以后，哆啦A梦就想尽办法要帮助野比大雄获得静香的芳心。",
    "\r\n正当源静香总算答应了野比大雄的求婚的时候，任务完成的哆啦A梦却被完成程式要求，要在48小时内回到22世纪。难道，得到了什么，自然的，也会失去些什么这个命定的预言，没办法被哆啦A梦跟野比大雄突破。面对哆啦A梦即将离开的冲击，野比大雄又该如何自处。"
  ],
  "user_intros": [
    {
      "job": "主角",
      "name": "ドラえもん / 哆啦A梦",
      "cv": [
        "水田わさび",
        "林保全"
      ]
    },
    {
      "job": "主角",
      "name": "野比のび太 / 野比大雄",
      "cv": [
        "大原めぐみ",
        "妻夫木聡"
      ]
    },
    {
      "job": "主角",
      "name": "源静香 / 源静香",
      "cv": [
        "かかずゆみ"
      ]
    },
    {
      "job": "配角",
      "name": "剛田武 / 刚田武",
      "cv": [
        "木村昴"
      ]
    },
    {
      "job": "配角",
      "name": "骨川スネ夫 / 骨川小夫",
      "cv": [
        "関智一"
      ]
    },
    {
      "job": "配角",
      "name": "野比のび助 / 野比大助",
      "cv": [
        "松本保典"
      ]
    },
    {
      "job": "配角",
      "name": "野比玉子 / 野比玉子",
      "cv": [
        "三石琴乃"
      ]
    },
    {
      "job": "配角",
      "name": "出木杉英才 / 出木杉英才",
      "cv": []
    }
  ],
  "complaints": [
    "补标",
    "小时候看哭了",
    "看哭了，别的不记得",
    "还行",
    "补标",
    "这居然是14年的",
    "把优秀篇章杂糅在一起，像五仁月饼",
    "谎言800啊",
    "电影上映都是2014年了，居然快十年了吗...",
    "补标"
  ],
  "comments": []
}